{
    "Clinical Trial ID": "NCT00383500",
    "Intervention": [
        "干预一:",
        "灵活设备",
        "通过Flexitouch设备管理淋巴肿瘤,一次性气压压缩装置(也称为淋巴肿瘤泵)",
        "干预2:",
        "手动淋巴排水(MLD)",
        "通过自给自足的手动淋巴排水疗法的淋巴肿瘤管理"
    ],
    "Eligibility": [
        "融入标准:",
        "单边乳腺癌",
        "计划进行乳房手术和轴心淋巴结分解,有或没有乳房保存技术。",
        "提到斯坦福大学乳腺癌计划的外科医生",
        "提供知情同意的能力。",
        "所有实验协议都将由斯坦福人体保护机构审查委员会审查和批准。",
        "排除标准:",
        "其他严重的系统性疾病(肾功能衰竭,肝功能障碍,心脏衰竭,神经学或心理障碍),会使研究混淆或影响患者参与的能力。",
        "重复性乳腺癌或其他形式的现有淋巴瘤。"
    ],
    "Results": [
        "测量结果:",
        "通过多频生物阻碍光谱测量成功评估淋巴肿的参与者数量",
        "成功的连续多频生物阻碍性评估新发育的淋巴肿瘤在3个研究组",
        "时间框架:36个月",
        "结果一:",
        "品牌名称: Flexitouch 设备",
        "手臂/组描述:通过Flexitouch设备管理淋巴肿瘤,一个间歇性气动压缩设备(也称为淋巴肿瘤泵)",
        "分析参与者总数:19人",
        "尺寸类型: 数字",
        "单位:参与者19人",
        "结果二:",
        "手动淋巴排水(MLD)",
        "手臂/组描述:通过自给自足的手动淋巴排水疗法来管理淋巴肿瘤",
        "分析的参与者总数: 21",
        "尺寸类型: 数字",
        "测量单位:参与者 21"
    ],
    "Adverse Events": [
        "意外事件一:",
        "总数: 0/19 (0.00%)",
        "不利事件二:",
        "总共:"
    ]
}