{
    "Clinical Trial ID": "NCT00317720",
    "Intervention": [
        "干预一:",
        "特拉斯图苏马布 + RAD001",
        "Trastuzumab的加载剂量为8 mg/kg;维持剂量 = 6 mg/kg每21天的周期一次。"
    ],
    "Eligibility": [
        "融入标准:",
        "生物检验证明HER-2过度表达乳腺癌的历史和转移性疾病的X射线证据。HER-2状态可以通过免疫组织化(分数3+)或现场荧光混合化来确定。",
        "抗特拉斯图zumab病史,定义为在基于特拉斯图zumab治疗转移性乳腺癌后发展进展性疾病,患者可能没有接受过超过2种以特拉斯图zumab为基础的治疗方案和1种基于拉帕蒂尼布的治疗方案(作为单剂或与化疗结合)用于转移性乳腺癌。",
        "绩效状态 0-2 (根据东部合作肿瘤学小组(ECOG)等级)。",
        "绝对中性细胞数(ANC) 1500/μl 或更高; 血小板 100,000/μl 或更高; 血红蛋白 9.0 gm/dL 或更高; 血清激素 2.0 mg/dL 或更低; 总 bilirubin 1.5 mg/dL 或更低; 血清 glutamic pyruvic transaminase (SGPT) 至 3 * 正常的上限; 碱性磷酸盐 至 3 * 正常的上限; 钙 11.0 mg/dL 或更低。",
        "18岁或以上。",
        "怀孕测试将得到,如果病人是一个孕育能力的女性,定义为没有接受过歇斯特雷克托米的性成熟妇女,或至少连续24个月没有自然发生过更年期后期(即在前24个月中有月经的女性)。",
        "患者必须签署一份知情同意文件,说明他们了解所建议的治疗的调查性质。",
        "患者必须使用固体肿瘤的响应评估标准(RECIST)进行测量。可测量的疾病被定义为至少有一种损伤,可以用常规技术准确测量至少一个尺寸的最长直径 >/= 20 毫米或 >/= 10 毫米的螺旋计算机扫描(CT)扫描。",
        "患者可能不接受任何其他调查代理,并不得在报名后15天内收到调查代理。",
        "通过心电图或多重获取(MUGA)(心脏扫描)确定的左心室排出比例必须为50%或更高。",
        "排除标准:",
        "未经控制的间歇性疾病,包括但不限于持续或活跃的感染,症状性拥堵性心力衰竭,不稳定的喉咙痛,心脏动荡,或精神疾病 / 社会情况,将限制遵守研究要求",
        "在前15天内使用任何研究药物",
        "慢性治疗系统类固醇或其他免疫抑制剂",
        "未经控制的大脑或骨髓膜转移,包括持续需要葡萄糖剂治疗大脑或骨髓膜转移的患者,以及在3个月内诊断出脑或骨髓膜疾病(LMD)的患者。",
        "过去3年内的其他恶性疾病,除了适当治疗的宫颈癌或基状或皮肤细胞癌。",
        "已知的艾滋病毒阳性历史",
        "胃肠道功能或胃肠道疾病的损害,可能显著改变RAD001的吸收(例如,溃性疾病,不受控制的恶心,呕吐,腹泻,吸收不良综合征或小肠切除)",
        "患有活性、出血性腹泻或服用口服抗维生素K药物的患者(低剂量的库马丁除外)",
        "曾接受过mTor抑制剂治疗的患者。",
        "未遵守医疗制度的历史。",
        "患者不愿意或无法遵守该协议。",
        "正在接受任何其他研究剂的患者",
        "患者表现出混淆,迷路,或有重大精神疾病的历史,可能影响了解知情同意。"
    ],
    "Results": [
        "测量结果:",
        "RAD001 与 Trastuzumab 结合的最佳剂量(第一阶段)",
        "在第一阶段,研究了RAD001的两种剂量水平:10 mg(剂量级别1)和5 mg(剂量级别-1),在MDACC中,连续重新评估方法(CRM)用于确定最大容忍剂量(MTD)应用于两种预先定义的RAD001剂量水平;在DFCI/BIDMC中,使用了3x3研究设计。",
        "最佳剂量定义为与0.20的毒性率最密切相关的剂量,毒性定义为任何3级或4级的毒性(基于共同术语标准(CTC)版本 3.0,除疲劳外。",
        "时间框架:经过两周的治疗周期",
        "结果一:",
        "手臂/组名称:Trastuzumab + RAD001",
        "手臂/组 描述:Trastuzumab的加载剂量为8 mg/kg 每天;维持剂量 = 6 mg/kg 每 21 天的周期一次 RAD001 10 mg PO (口服) 每天。",
        "分析参与者总数:19人",
        "尺寸类型: 数字",
        "测量单位: mg 10"
    ],
    "Adverse Events": [
        "意外事件一:",
        "总数: 47/47 (100.00%)",
        "贫血4/47(8,51%)",
        "淋巴嫩症 13/47 (27.66%)",
        "神经衰竭 9/47 (19.15%)",
        "血管细胞期4/47(8,51%)",
        "腹泻 9/47 (19.15%)",
        "疲劳 9/47 (19.15%)",
        "糖尿病 13/47 (27.66%)",
        "低血压症 6/47 (12.77%)",
        "超脂肪率4/47(8,51%)",
        "感染 4/47 (8.51%)",
        "肝炎 9/47 (19.15%)",
        "传染病 2/47 (4.26%)",
        "Thrombosis / 胚胎症 2/47 (4.26%)"
    ]
}