{
    "Clinical Trial ID": "NCT00278109",
    "Intervention": [
        "干预一:",
        "实验",
        "化合物:化疗",
        "多克索鲁比辛水氯化物:化疗",
        "辅助疗法:化疗",
        "辐射疗法:化疗"
    ],
    "Eligibility": [
        "疾病特征:",
        "乳腺腺癌通过例行血酸素和素(H&E)染色来确认",
        "初级肿瘤 4 cm 和 0-3 阳性轴心淋巴结(病理 T1-2,病理 N0-N1, M0)",
        "只有 cytokeratin 染色(即 H&E 负)的淋巴结阳性患者有资格",
        "没有乳腺细胞癌或乳腺",
        "患者必须在过去14周内接受一级I和一级LL轴心分解或指针淋巴结生物检。",
        "SM时的手术差距必须为负(>3毫米)在侵入性癌症和非侵入性管道癌症",
        "没有活跃的区域性疾病",
        "激素受体状态未确定",
        "患者特点:",
        "ECOG绩效状态 0-1",
        "性别:女性",
        "更年期状态未明确",
        "没有怀孕",
        "负妊娠测试",
        "生育的患者必须使用有效的非荷尔蒙避孕药",
        "在过去5年内没有其他恶性疾病,除了适当治疗的基细胞或皮肤细胞皮肤癌或子宫颈癌",
        "没有其他严重或不受控制的医疗或精神病状况,可能会加重或使遵守研究治疗变得困难。",
        "竞争对手治疗:",
        "没有先前放射治疗乳房",
        "没有先前的特拉斯图苏马布(Herceptin®)",
        "没有其他竞争性化疗",
        "除以下外,没有同步激素治疗:",
        "用于肾上腺衰竭的类固醇",
        "用于非疾病相关疾病的激素(例如,糖尿病的胰岛素,甲状腺衰竭的合成剂)",
        "间歇性 dexamethasone作为抗药或预药"
    ],
    "Results": [
        "测量结果:",
        "经历急性、晚期皮肤和皮下毒性的参与者数量",
        "根据以下标准定义的4级毒性参与者数量:",
        "急性皮肤毒性: 0 = 没有变化, 1 =  Folicular, 薄弱, 或 枯燥的皮疹 / 脱发 / 干燥 / 脱发 / 减轻的肿胀, 2 = 温和或明亮的皮肤湿润的脱发 / 适度的肿瘤, 3 = 冲动湿的脱发, 除皮肤折叠, 皮肤肿瘤, 4 = 溃, 出血, 结核, 晚期皮肤毒性: 0 = 无, 1 = 轻微性侵蚀, 颜色变化, 一些头发损失, 2 = 皮肤性侵蚀, 适度的电甘卡萨, 整体头发损失, 3 = 标志性萎缩, 大型电甘卡萨, 4 = 溃; 皮下",
        "时间框架:最多5年",
        "结果一:",
        "品牌名称: 实验",
        "手臂/组 描述: cyclophosphamide:化疗",
        "多克索鲁比辛水氯化物:化疗",
        "辅助疗法:化疗",
        "辐射疗法:化疗",
        "分析的参与者总数:25人",
        "活动类型:参与人数",
        "测量单位: 参与者 0 0.0%"
    ],
    "Adverse Events": [
        "意外事件一:",
        "总数: 1/25 (4.00%)",
        "中性衰竭 *1/25 (4.00%)"
    ]
}