{
    "Clinical Trial ID": "NCT00390455",
    "Intervention": [
        "干预一:",
        "手臂I(拉帕提尼布)",
        "患者在1至28天服用1500毫克拉帕蒂尼布Ditosylate PO QD,并在1日(500毫克)和15日(250毫克)服用Fulvestrant IM,并在1日(250毫克)的每一个后续疗程。",
        "干预2:",
        "手臂II(安慰剂)",
        "患者在第1至28天接受了安慰剂 PO QD,并在第1天(500 mg)和第15天(250 mg)接受了Fulvestrant IM,并在每一次后续疗程的第1天(250 mg)服用。"
    ],
    "Eligibility": [
        "融入标准:",
        "妇女乳腺癌在初级或转移性环境中的历史学、病理学或细胞学诊断;如果有明确的临床证据表明复发,则不需要进行转移性/复发性疾病的历史学记录。",
        "四级乳腺癌(使用美国联合癌症委员会(AJCC)标准,第六版)或本地先进(第三阶段)乳腺癌不被认为可治疗",
        "患有症状性大脑转移或其他症状性中枢神经系统(CNS)转移的患者不符合研究资格;无症状患者不需要进行筛查研究;已接受过治疗的大脑转移的患者,他们没有与中枢神经系统疾病有关的症状,并且在大脑转移治疗后 > 3 个月的患者有资格。",
        "肿瘤(根据从主要或转移点的病理学确定)必须对内分泌疗法有潜在的敏感性,定义为表达雌激素受体(ER)和/或 progesterone 受体(PgR)作为根据当地机构的标准协议确定的免疫 histochemical 方法, >= 1% 细胞将被视为阳性。",
        "该协议已被修改以允许任何HER2状态的肿瘤,尽管HER2状态必须确定;如果HER2表达通过下列方法之一进行记录,患者将被视为符合条件的:",
        "免疫歇斯托化学(IHC)0(即负),1+,2+,或3+表达水平,或",
        "基因放大(荧光在现场混合(FISH))积极或消极",
        "患者必须至少有一个损伤,可以准确地测量至少一个维度(最长的直径要记录) >= 2.0 cm 用传统技术或 >= 1.0 cm 用螺旋计算机扫描(CT)扫描",
        "例外:作为他们唯一的疾病站点的乳骨或骨转移的患者将有资格参加研究,即使这些患者不被认为根据固体肿瘤响应评估标准(RECIST)的标准具有可测量的疾病;这些患者将可以评估时间到进展,但没有响应",
        "患有所有其他损伤的患者,包括小损伤(最长直径 < 2.0 cm 用常规技术或 < 1.0 cm 用螺旋 CT 扫描)和真正无法测量的损伤,包括下面列出的损伤,不符合条件。",
        "被认为是不可测量的损伤包括以下几点:",
        "骨骼损伤(骨骼损伤的女性将符合上述规定)",
        "Leptomeningeal 疾病",
        "升华",
        "肺部 / 周心脏排泄",
        "炎症性乳腺癌",
        "肺炎 / 肺炎",
        "未确认的腹部质量,随后采用成像技术",
        "细胞损伤",
        "患者必须在辅助性或转移性环境中先前进行一两次乳腺癌内分泌治疗,不包括与治疗相关的失血症或卵巢抑制;连续使用两种不同的第三代芳香酶抑制剂被视为“一”治疗;肿瘤不需要对此类治疗具有抵抗性;例如:",
        "一个从未接受过内分泌疗法的 de novo 转移性乳腺癌患者不符合条件;",
        "接受辅助酮和随后用 aromatase 抑制剂(辅助剂或转移剂)治疗的患者有资格;",
        "一名在辅助性或转移性环境中服用 aromatase 抑制剂的患者,并因副作用在几个月后中止治疗,有资格;",
        "在辅助设置中服用阿罗马塔酶抑制剂的患者有资格,无论他们是否在某一时刻服用tamoxifen;",
        "一名患者接受辅助剂Tamoxifen,并随后接受辅助剂或转移性环境中先进乳腺癌的非固醇芳香酸抑制剂和固醇芳香酸抑制剂的资格;",
        "接受补充剂Tamoxifen,然后非固醇阿罗马塔酶抑制剂,并随后用于前进乳腺癌的Megesterol acetate的患者不符合条件",
        "对内分泌疗法潜在敏感的肿瘤,定义为以前的内分泌疗法超过3个月,在辅助性或转移性环境中没有疾病进展",
        "患者必须先前在辅助或转移环境中使用商业上可用的第三代芳香酶抑制剂(即 anastrozole、exemestane 或 letrozole)进行治疗;肿瘤不需要对这些疗法具有耐药性。",
        "患者可能已接受多达一项之前的四级乳腺癌化疗方案;预先在辅助剂和/或新辅助剂设置中进行化疗是允许的;患者必须在开始基于协议的治疗前至少1周完成化疗。",
        "患者可能已接受过以往的Trastuzumab治疗IV阶段乳腺癌,并与最多一次化疗和/或内分泌治疗方案相结合,但必须在开始基于协议的治疗之前至少完成3周;在辅助剂和/或新辅助剂设置中允许先前的Trastuzumab治疗,但必须在开始基于协议的治疗之前至少完成3周。",
        "禁止使用商业上可用的EGFR抑制剂(包括但不限于盖菲蒂尼布、埃尔洛蒂尼布、拉帕蒂尼布或凯图西马布)或实验性EGFR抑制剂。",
        "在研究入学前,患者可能已经开始了双磷酸盐治疗;这些患者将有骨骼损伤被认为可评估的进展,但不是响应。",
        "早期治疗是禁止的。",
        "接受卵巢抑制的 gonadotropin-releasing hormone (GnRH) 激活剂的患者必须在整个协议治疗期间继续服用这种疗法;患者必须在进入研究之前停止其他内分泌治疗,包括系统性激素替代疗法和体内雌激素;患者必须在进入研究之前完成放射治疗;患者必须在之前接受化疗至少1周或之前服用trastuzumab至少3周,骨髓功能和性能状况得到充分恢复。",
        "患者必须是更年期后女性,定义为满足下列任何标准的女性:",
        "年龄 > = 60 岁;或",
        "年龄 >= 45 岁,未受损的子宫和12 个月或更长时间的缺血;或",
        "双边鸦片切除的历史;或",
        "刺激激素(FSH)水平在更年期后范围内,根据测试设施确定的范围;或",
        "在研究登记前至少连续3个月使用GnRH激活剂用于抑制卵巢,并在整个协议治疗过程中继续使用此类治疗",
        "孕妇或哺乳期妇女不适合参加这项研究;临床医生应该提醒患者,在孕妇中没有关于拉帕蒂尼布或富尔维斯特兰的安全性数据,也没有关于这些药物对生育或怀孕的影响的数据。",
        "东部合作肿瘤学小组(ECOG)(Zubrod)绩效状态 0-2",
        "缺乏即将发生的阴道危机,根据治疗医生的看法",
        "没有获得或遗传的出血障碍",
        "缺乏治疗系统抗凝血剂的必要性(定义为维持国际正常化比率(INR) > 1.6);患者可以服用低剂量的华法林或阿司匹林(或同等剂量)以维持中央静脉电梯通度",
        "颗粒细胞 > = 1000/μl",
        "血管數量 > = 100,000/μl",
        "素 = < 2 mg/dl",
        "总 bilirubin = < 1.5 x 正常的上限(ULN)除非由于吉尔伯特综合征",
        "阿斯巴达氨基转移酶(AST)和阿拉宁氨基转移酶(ALT) = < 2.5 x ULN 无肝转移; = < 5 x ULN 与肝转移",
        "INR = < 1.6",
        "左腹部排泄部分(LVEF)在正常的机构范围内"
    ],
    "Results": [
        "测量结果:",
        "无进展生存(PFS)",
        "PFS被定义为从研究入学到疾病进展或死亡的间隔,因任何原因而导致,从前发生,进展被定义为目标损伤最长直径总量的20%增加(按RECIST标准)。",
        "时间框架:从随机化到疾病进展或死亡的间隔,取决于先发生,估计最多为5年",
        "结果一:",
        "手臂/组名称:手臂I(拉帕提尼布)",
        "手臂/组描述:患者在1至28天服用1500毫克拉帕蒂尼布Ditosylate PO QD,并在1日(500毫克)和15日(250毫克)服用Fulvestrant IM,并在1日(250毫克)的每一个后续疗程。",
        "参与者分析总数:146人",
        "平均(95%的信任间隔)",
        "衡量单位: 4.7 个月(3.7 到 5.7)",
        "结果二:",
        "手臂/组名称:手臂II(Placebo)",
        "手臂/组描述:患者在1日至28日服用安慰剂 PO QD,并在1日(500 mg)和15日(250 mg)服用Fulvestrant IM,并在1日(250 mg)服用每个随后的疗程。",
        "分析的参与者总数:145人",
        "平均(95%的信任间隔)",
        "衡量单位: 3.8 个月(3.8 到 5.6)"
    ],
    "Adverse Events": [
        "意外事件一:",
        "总数: 12/141(8,51%)",
        "心脏疼痛 1/141 (0.71%)",
        "感冒 1/141 (0.71%)",
        "腹泻 7/141 (4.96%)",
        "胃肠道疾病 0/141 (0.00%)",
        "恶心 5/141 (3.55%)",
        "吐槽 2/141 (1.42%)",
        "胸部疼痛 1/141 (0.71%)",
        "疾病进展率 1/141 (0.71%)",
        "疲劳 8/141 (5.67%)",
        "不正常的步伐 0/141 (0.00%)",
        "注射站反應 1/141 (0.71%)",
        "疼痛 1/141 (0.71%)",
        "不利事件二:",
        "总数: 14/137 (10.22%)",
        "心脏疼痛 1/137 (0.73%)",
        "感冒 2/137 (1.46%)",
        "腹泻 4/137 (2.92%)",
        "胃肠道疾病 1/137 (0.73%)",
        "恶心 3/137 (2.19%)",
        "呕吐 1/137 (0.73%)",
        "胸部疼痛 1/137 (0.73%)",
        "疾病进展 0/137 (0.00%)",
        "疲劳 5/137 (3.65%)",
        "不正常的步伐 1/137 (0.73%)",
        "注射站反應 0/137 (0.00%)",
        "疼痛2/137(1.46%)"
    ]
}