{
    "Clinical Trial ID": "NCT00297596",
    "Intervention": [
        "干预一:",
        "牛皮癣/特拉斯图",
        "HER2 阳性乳腺癌患者在 IV 第一天接受 Oxaliplatin 130 mg/m2 和 trastuzumab 6 mg/kg 治疗(在 1 周期内服用 8 mg/kg 的加载剂量)。周期每 21 天重复使用 Oxaliplatin : Oxaliplatin 将在每周期的 1 天服用 130 mg/m2 的剂量,在 120 分钟内服用标准抗药。 21 天的周期。 在 1 周期中服用 trastuzumab 之前服用 oxaliplatin;然而,在随后的周期中,oxaliplatin 将服用 trastuzumab 之前服用 trastuzumab : Trastuzumab 将服用 8 mg/kg 的加载剂量,在 1 周期 1 天服用 intravenous (IV) 注射"
    ],
    "Eligibility": [
        "融入标准:",
        "女性18岁以上",
        "histologically confirmed breast cancer that is HER2/neu positive (3+ by IHC or FISH +) and evidence of metastatic disease. 肿瘤可能是任何类型的雌激素和 progesterone受体",
        "通过RECIST和ECOG2测量疾病",
        "有已知大脑转移的证据的患者是符合条件的,如果他们是无症状的,并已完成所有治疗(手术,放射治疗和 / 或类固醇)",
        "基准 LVEF 值在机构正常范围内",
        "任何之前的激素治疗在辅助设置或转移性疾病的治疗。 一个受试者必须已经在激素治疗和所有激素治疗(包括避孕药)必须停止在研究的入学。",
        "允许先前化疗在辅助设置和多达一个先前化疗方案的转移性疾病。",
        "患者可能曾接受过一次以前含有治疗方案的拉斯图苏马布/化疗或之前的单剂拉斯图苏马布。",
        "预先在辅助环境或转移性疾病中进行放射治疗,前提是它不是唯一可评估的疾病地点。",
        "所有之前的化疗,拉斯图苏马布和放射治疗应在注册前2周完成。",
        "接受双磷酸盐治疗的患者有资格接受治疗,但是,如果双磷酸盐治疗在注册前2个月内开始,骨骼损伤将不会被评估为响应,并且患者必须有另一个可测量或可评估的转移性疾病场所。",
        "患者必须因先前治疗而从毒性中恢复。",
        "根据协议的实验室值",
        "非孕妇和非母乳喂养的患者必须在研究期间实施有效的避孕方法(避孕药不允许)。",
        "排除标准:",
        "只有骨骼疾病是不合格的",
        "接受先前1次以上的转移性疾病化疗方案的患者不符合条件。",
        "患有其他癌症的病史,除了在现场治疗的宫颈癌或非黑色素皮肤癌。",
        "活跃的严重感染或其他潜在的医疗状况,会影响他们接受协议治疗的能力。",
        "神经系统不受控制的转移",
        "痴呆症或显著改变的心理状态,会干扰适当的同意。",
        "接受其他研究疗法。"
    ],
    "Results": [
        "测量结果:",
        "客观响应率(ORR):患者从治疗中获得客观好处的百分比",
        "针对目标损伤的固体肿瘤评估标准(RECIST v1.0)和通过MRI或CT评估:完全响应(CR),所有目标损伤的消失;部分响应(PR),目标损伤最长直径的总和 >=30%下降;总响应(OR) = CR + PR。",
        "时间框架:18个月",
        "结果一:",
        "手臂/组名称: Oxaliplatin/Trastuzumab",
        "手臂/组 描述:HER2 阳性乳腺癌患者在 IV 第一天接受 Oxaliplatin 130 mg/m2 和 trastuzumab 6 mg/kg 治疗(在 1 周期内服用 8 mg/kg 加载剂)。 周期每 21 天重复使用 Oxaliplatin : Oxaliplatin 将在每周期的 1 天服用 130 mg/m2 的剂量,每周期内服用 120 分钟,然后服用标准的抗药剂。 21 天的周期。 在 1 周期中服用 trastuzumab 将在 oxaliplatin 之前服用;然而,在随后的周期中,oxaliplatin 将服用 trastuzumab 之前服用 trastuzumab : Trastuzumab 将服用 8 mg/kg 加载剂",
        "分析的参与者总数:25人",
        "尺寸类型: 数字",
        "衡量单位:参与者的百分比 20(4.3 至 35.7)"
    ],
    "Adverse Events": [
        "意外事件一:",
        "总数: 7 / 25 (28.00%)",
        "穿孔附件 1/25 (4.00%)",
        "过敏反应 1/25(4.00%)",
        "疏远近角膜膜 1/25(4.00%)的病理性骨折",
        "右接近肢膜膜膜 1/25(4.00%)的病理性骨折",
        "呼吸衰竭次要于转移性疾病 1/25 (4.00%)",
        "乳腺癌 1/25(4.00%)",
        "进展性疾病 1/25 (4.00%)"
    ]
}